Sephiroth.py
sephiroth/__init__.py
sephiroth/__pycache__/__init__.cpython-312.pyc
sephiroth/providers/__init__.py
sephiroth/providers/asn.py
sephiroth/providers/aws.py
sephiroth/providers/azure.py
sephiroth/providers/base_provider.py
sephiroth/providers/cloudflare.py
sephiroth/providers/do.py
sephiroth/providers/file.py
sephiroth/providers/gcp.py
sephiroth/providers/linode.py
sephiroth/providers/oci.py
sephiroth/providers/provider.py
sephiroth/providers/tor.py
sephiroth/templates/apache/conf.jinja
sephiroth/templates/apache/help.jinja
sephiroth/templates/caddy1/conf.jinja
sephiroth/templates/ip6tables/conf.jinja
sephiroth/templates/ip6tables/help.jinja
sephiroth/templates/iptables/conf.jinja
sephiroth/templates/iptables/help.jinja
sephiroth/templates/nginx/conf.jinja
sephiroth/templates/nginx/help.jinja
sephiroth-1.0.4.dist-info/LICENSE
sephiroth-1.0.4.dist-info/METADATA
sephiroth-1.0.4.dist-info/WHEEL
sephiroth-1.0.4.dist-info/entry_points.txt
sephiroth-1.0.4.dist-info/top_level.txt
sephiroth-1.0.4.dist-info/RECORD
