Metadata-Version: 2.1
Name: sephiroth
Version: 1.0.4
Summary: Utility for building blocklists for ip ranges
Home-page: https://github.com/0xdade/sephiroth
Author: 0xdade
Author-email: dade@actualcrimes.org
Maintainer: 0xdade
Classifier: Programming Language :: Python :: 3.6
Classifier: Programming Language :: Python :: 3.7
Classifier: Programming Language :: Python :: 3.8
Classifier: Programming Language :: Python :: 3.9
Classifier: Programming Language :: Python :: 3.10
Classifier: Programming Language :: Python :: 3.11
Classifier: Programming Language :: Python :: 3.12
Requires-Python: >=3.6
License-File: LICENSE
Requires-Dist: beautifulsoup4 ~=4.11.1
Requires-Dist: requests ~=2.27.1
Requires-Dist: Jinja2 ~=3.1.1
Requires-Dist: netaddr ~=0.8.0
